AUTHORS
MANIFEST.in
README.md
setup.py
django_request_mock.egg-info/PKG-INFO
django_request_mock.egg-info/SOURCES.txt
django_request_mock.egg-info/dependency_links.txt
django_request_mock.egg-info/not-zip-safe
django_request_mock.egg-info/top_level.txt
request_mock/__init__.py