Metadata-Version: 1.1
Name: django-request-mock
Version: 0.1.3
Summary: Create a Django request object that mocks a real one.
Home-page: https://github.com/valeriansaliou/django-request-mock
Author: Valérian Saliou
Author-email: valerian@valeriansaliou.name
License: MIT - http://opensource.org/licenses/mit-license.php
Platform: UNKNOWN
Classifier: Development Status :: 3 - Alpha
Classifier: Environment :: Web Environment
Classifier: Framework :: Django
Classifier: Intended Audience :: Developers
Classifier: Natural Language :: English
Classifier: Programming Language :: Python
